core/__init__.py
core/interpreter.py
core/__pycache__/__init__.cpython-313.pyc
core/__pycache__/interpreter.cpython-313.pyc
core/features/code_templates.py
core/features/syntax_highlighting.py
core/features/__pycache__/syntax_highlighting.cpython-313.pyc
core/languages/__init__.py
core/languages/basic.py
core/languages/forth.py
core/languages/javascript.py
core/languages/javascript_executor.py
core/languages/logo.py
core/languages/pascal.py
core/languages/perl.py
core/languages/pilot.py
core/languages/prolog.py
core/languages/python.py
core/languages/python_executor.py
core/languages/__pycache__/__init__.cpython-313.pyc
core/languages/__pycache__/basic.cpython-313.pyc
core/languages/__pycache__/forth.cpython-313.pyc
core/languages/__pycache__/javascript_executor.cpython-313.pyc
core/languages/__pycache__/logo.cpython-313.pyc
core/languages/__pycache__/pascal.cpython-313.pyc
core/languages/__pycache__/perl.cpython-313.pyc
core/languages/__pycache__/pilot.cpython-313.pyc
core/languages/__pycache__/prolog.cpython-313.pyc
core/languages/__pycache__/python_executor.cpython-313.pyc
core/optimizations/__init__.py
core/optimizations/gui_optimizer.py
core/optimizations/memory_manager.py
core/optimizations/performance_optimizer.py
core/optimizations/__pycache__/__init__.cpython-313.pyc
core/optimizations/__pycache__/gui_optimizer.cpython-313.pyc
core/optimizations/__pycache__/memory_manager.cpython-313.pyc
core/optimizations/__pycache__/performance_optimizer.cpython-313.pyc
core/utilities/__init__.py
core/utilities/__pycache__/__init__.cpython-313.pyc
timewarp_classic-1.3.0.dist-info/licenses/LICENSE
timewarp_classic-1.3.0.dist-info/METADATA
timewarp_classic-1.3.0.dist-info/WHEEL
timewarp_classic-1.3.0.dist-info/entry_points.txt
timewarp_classic-1.3.0.dist-info/top_level.txt
timewarp_classic-1.3.0.dist-info/RECORD
