Metadata-Version: 2.4
Name: timewarp-classic
Version: 1.3.0
Summary: Multi-language interpreter with turtle graphics support
Author-email: Honey Badger Universe <contact@honeybadgeruniverse.com>
License: MIT License
Project-URL: Homepage, https://github.com/James-HoneyBadger/Time_Warp_Classic
Project-URL: Documentation, https://github.com/James-HoneyBadger/Time_Warp_Classic/tree/main/docs
Project-URL: Repository, https://github.com/James-HoneyBadger/Time_Warp_Classic.git
Project-URL: Issues, https://github.com/James-HoneyBadger/Time_Warp_Classic/issues
Keywords: interpreter,turtle-graphics,educational,programming,languages
Classifier: Development Status :: 4 - Beta
Classifier: Intended Audience :: Education
Classifier: Operating System :: OS Independent
Classifier: Programming Language :: Python :: 3
Classifier: Programming Language :: Python :: 3.9
Classifier: Programming Language :: Python :: 3.10
Classifier: Programming Language :: Python :: 3.11
Classifier: Programming Language :: Python :: 3.12
Classifier: Programming Language :: Python :: 3.13
Classifier: Topic :: Education
Classifier: Topic :: Software Development :: Interpreters
Requires-Python: >=3.9
License-File: LICENSE
Requires-Dist: pygame>=2.0.0
Requires-Dist: Pillow>=8.0.0
Requires-Dist: pygments>=2.10.0
Provides-Extra: test
Requires-Dist: pytest>=7.0.0; extra == "test"
Requires-Dist: pytest-cov>=4.0.0; extra == "test"
Requires-Dist: pytest-mock>=3.10.0; extra == "test"
Requires-Dist: pytest-xdist>=3.0.0; extra == "test"
Dynamic: license-file
